winnow/__init__.py
winnow/constants.py
winnow/data_types.py
winnow/calibration/__init__.py
winnow/calibration/calibration_features.py
winnow/calibration/calibrator.py
winnow/datasets/__init__.py
winnow/datasets/calibration_dataset.py
winnow/datasets/data_loaders.py
winnow/datasets/interfaces.py
winnow/datasets/psm_dataset.py
winnow/fdr/__init__.py
winnow/fdr/base.py
winnow/fdr/database_grounded.py
winnow/fdr/nonparametric.py
winnow/scripts/__init__.py
winnow/scripts/main.py
winnow_fdr-1.0.3.dist-info/licenses/LICENSE.md
winnow_fdr-1.0.3.dist-info/METADATA
winnow_fdr-1.0.3.dist-info/WHEEL
winnow_fdr-1.0.3.dist-info/entry_points.txt
winnow_fdr-1.0.3.dist-info/top_level.txt
winnow_fdr-1.0.3.dist-info/RECORD
