Metadata-Version: 2.4
Name: winnow-fdr
Version: 1.0.3
Summary: Score calibration and false discovery estimation for de novo peptide sequencing.
Author: InstaDeep
License-Expression: Apache-2.0
Project-URL: Homepage, https://github.com/instadeepai/winnow
Project-URL: Issues, https://github.com/instadeepai/winnow/issues
Project-URL: documentation, https://instadeepai.github.io/winnow/
Keywords: proteomics,mass spectrometry,de novo peptide sequencing,false discovery rate,false discovery estimation,peptide filtering
Classifier: Programming Language :: Python :: 3
Classifier: Operating System :: OS Independent
Requires-Python: >=3.10
License-File: LICENSE.md
Requires-Dist: jax>=0.5.2
Requires-Dist: koinapy>=0.0.10
Requires-Dist: tomli>=2.2.1
Requires-Dist: typer>=0.15.2
Requires-Dist: instanovo>=1.1.4
Dynamic: license-file
